waterservices/__init__.py
waterservices/nwis/__init__.py
waterservices-0.1.1.dist-info/WHEEL
waterservices-0.1.1.dist-info/METADATA
waterservices-0.1.1.dist-info/RECORD
