Metadata-Version: 2.1
Name: waterservices
Version: 0.1.1
Summary: A pyhton package to work with WaterServices USGS
Home-page: https://github.com/javad-rzvn/waterservices
Author: javad-rzvn
Author-email: javad.rezvanpour@gmail.com
Requires-Python: >=3.7,<4.0
Classifier: Programming Language :: Python :: 3
Classifier: Programming Language :: Python :: 3.10
Classifier: Programming Language :: Python :: 3.7
Classifier: Programming Language :: Python :: 3.8
Classifier: Programming Language :: Python :: 3.9
Requires-Dist: dask (>=2022.2.0,<2023.0.0)
Requires-Dist: pandas (>=1.3.5,<2.0.0)
Requires-Dist: requests (>=2.27.1,<3.0.0)
Requires-Dist: tqdm (>=4.64.0,<5.0.0)
Project-URL: Repository, https://github.com/javad-rzvn/waterservices
